pysolarenergy/__init__.py
pysolarenergy/__version__.py
pysolarenergy/const.py
pysolarenergy/exceptions.py
pysolarenergy/inverter.py
pysolarenergy/parser.py
pysolarenergy-0.0.1.dist-info/LICENSE
pysolarenergy-0.0.1.dist-info/METADATA
pysolarenergy-0.0.1.dist-info/WHEEL
pysolarenergy-0.0.1.dist-info/top_level.txt
pysolarenergy-0.0.1.dist-info/RECORD
