Metadata-Version: 2.1
Name: pysolarenergy
Version: 0.0.1
Summary: Python module for SolarEnergy inverter
Home-page: https://github.com/hallenmaia/python-solarenergy
Author: Hallen Maia
Author-email: hallenmaia@me.com
License: MIT license
Keywords: api,async,client,inverter,solar
Platform: UNKNOWN
Classifier: Programming Language :: Python :: 3
Classifier: Programming Language :: Python :: 3.7
Classifier: Programming Language :: Python :: 3.8
Classifier: Framework :: AsyncIO
Classifier: Natural Language :: English
Classifier: License :: OSI Approved :: MIT License
Classifier: Topic :: Software Development :: Libraries :: Python Modules
Requires-Python: >=3.7
Requires-Dist: aiohttp (~=3.6.2)
Requires-Dist: xmltodict (~=0.12.0)
Requires-Dist: yarl (~=1.4.2)
